LICENSE
MANIFEST.in
flask_fds.py
setup.cfg
setup.py
Flask_FDS.egg-info/PKG-INFO
Flask_FDS.egg-info/SOURCES.txt
Flask_FDS.egg-info/dependency_links.txt
Flask_FDS.egg-info/not-zip-safe
Flask_FDS.egg-info/requires.txt
Flask_FDS.egg-info/top_level.txt