Metadata-Version: 1.1
Name: Flask-FDS
Version: 0.0.1
Summary: Xiaomi File Storage Service for Flask
Home-page: https://coding.net/u/lvzhaoxing/p/Flask-FDS
Author: Lv Zhaoxing
Author-email: lvzhaoxing@qq.com
License: MIT
Keywords: fds for flask
Platform: any
Classifier: Development Status :: 4 - Beta
Classifier: Environment :: Web Environment
Classifier: Intended Audience :: Developers
Classifier: License :: OSI Approved :: MIT License
Classifier: Operating System :: OS Independent
Classifier: Programming Language :: Python
Classifier: Topic :: Internet :: WWW/HTTP :: Dynamic Content
Classifier: Topic :: Software Development :: Libraries :: Python Modules
